README.rst
setup.cfg
setup.py
optimized_image/__init__.py
optimized_image/admin.py
optimized_image/apps.py
optimized_image/fields.py
optimized_image/models.py
optimized_image/urls.py
optimized_image/utils.py
optimized_image/views.py
optimized_image.egg-info/PKG-INFO
optimized_image.egg-info/SOURCES.txt
optimized_image.egg-info/dependency_links.txt
optimized_image.egg-info/requires.txt
optimized_image.egg-info/top_level.txt
optimized_image/migrations/0001_initial.py
optimized_image/migrations/0002_auto_20160715_1428.py
optimized_image/migrations/0003_optimizednotoptimized.py
optimized_image/migrations/0004_auto_20160715_1806.py
optimized_image/migrations/0005_optimizednotoptimized_field_name.py
optimized_image/migrations/0006_auto_20160715_1913.py
optimized_image/migrations/0007_delete_blogpostorsomething.py
optimized_image/migrations/__init__.py
optimized_image/tests/__init__.py
optimized_image/tests/factories.py
optimized_image/tests/test_fields.py
optimized_image/tests/test_models.py
optimized_image/tests/test_utils.py