Metadata-Version: 1.1
Name: optimized-image
Version: 0.0.1
Summary: A simple Django app that allows for optimization of images.
Home-page: https://github.com/dchukhin/django_tinypng
Author: Dmitriy Chukhin
Author-email: dchukhin@caktusgroup.com
License: BSD License
Download-URL: https://github.com/dchukhin/django_tinypng/tarball/0.0.1
Keywords: django,image,optimize,imagefield
Platform: UNKNOWN
Classifier: Environment :: Web Environment
Classifier: Framework :: Django
Classifier: Intended Audience :: Developers
Classifier: License :: OSI Approved :: BSD License
Classifier: Operating System :: OS Independent
Classifier: Programming Language :: Python
Classifier: Programming Language :: Python :: 3
Classifier: Programming Language :: Python :: 3.4
Classifier: Programming Language :: Python :: 3.5
Classifier: Topic :: Internet :: WWW/HTTP
Classifier: Topic :: Internet :: WWW/HTTP :: Dynamic Content
